spatialSNV.py
spatialsnvtools/CallBack.py
spatialsnvtools/PerpareBAMforCalling.py
spatialsnvtools/SNVCalling.py
spatialsnvtools/SplitChromBAM.py
spatialsnvtools/__init__.py
spatialsnvtools/cli.py
spatialsnvtools/log.py
spatialsnvtools/utils.py
spatialsnv-1.1.3.dist-info/LICENSE
spatialsnv-1.1.3.dist-info/METADATA
spatialsnv-1.1.3.dist-info/WHEEL
spatialsnv-1.1.3.dist-info/entry_points.txt
spatialsnv-1.1.3.dist-info/top_level.txt
spatialsnv-1.1.3.dist-info/RECORD
