Metadata-Version: 2.1
Name: spatialsnv
Version: 1.1.3
Summary: A toolkit for spatial SNV analysis
Home-page: https://github.com/YoungLi88/SpatialSNV
Author: Yi Liu
Author-email: liuyi6@genomics.cn
License: MIT
Classifier: Programming Language :: Python :: 3
Classifier: License :: OSI Approved :: MIT License
Classifier: Operating System :: OS Independent
Classifier: Intended Audience :: Developers
Classifier: Intended Audience :: Science/Research
Classifier: Topic :: Scientific/Engineering :: Bio-Informatics
Requires-Python: >=3.7
License-File: LICENSE
Requires-Dist: multiprocess==0.70.17
Requires-Dist: click==8.1.8
Requires-Dist: pysam==0.22.1
Requires-Dist: pandas==1.5.3
Requires-Dist: numpy==1.24.4
Requires-Dist: scikit-learn==1.4.1.post1
Requires-Dist: scipy==1.11.4
Requires-Dist: igraph==0.11.5
Requires-Dist: seaborn==0.13.2
Requires-Dist: matplotlib==3.7.5
Requires-Dist: scanpy==1.10.0
Requires-Dist: tqdm
Requires-Dist: cairocffi
Requires-Dist: pycairo
Requires-Dist: leidenalg
